{
  "id": "kent-group",
  "label": "Kent Group Demo",
  "description": "Sample customer, project, and PDF reference deck for quick testing.",
  "profile_id": "koncept",
  "pricing_reference_id": "koncept-exhibition-quotation",
  "images": [
    "kent-group.pdf"
  ],
  "details": {
    "client": {
      "name": "Kent Group",
      "attention": "Kent Group Team",
      "title": "Project Team",
      "address": "Singapore"
    },
    "project": {
      "title": "RE: Kent Group Exhibition Booth",
      "show_name": "SAMPLE"
    },
    "project_number": "KI-SAMPLE-001",
    "rich_text": {
      "clientName": "<div><strong>Kent Group</strong></div>",
      "clientAttention": "<div><strong>Kent Group Team</strong></div>",
      "clientTitle": "<div>Project Team</div>",
      "clientAddress": "<div>Singapore</div>",
      "projectTitle": "<div><strong>RE: Kent Group Exhibition Booth</strong></div>",
      "projectNumber": "<div>KI-SAMPLE-001</div>"
    }
  }
}
